odoo/addons/ssi_project_work_log/README.rst
odoo/addons/ssi_project_work_log/__init__.py
odoo/addons/ssi_project_work_log/__manifest__.py
odoo/addons/ssi_project_work_log/models/__init__.py
odoo/addons/ssi_project_work_log/models/project_project.py
odoo/addons/ssi_project_work_log/static/description/icon.png
odoo/addons/ssi_project_work_log/views/project_project_views.xml
odoo14_addon_ssi_project_work_log-14.0.1.1.0.dist-info/METADATA
odoo14_addon_ssi_project_work_log-14.0.1.1.0.dist-info/WHEEL
odoo14_addon_ssi_project_work_log-14.0.1.1.0.dist-info/top_level.txt
odoo14_addon_ssi_project_work_log-14.0.1.1.0.dist-info/RECORD
